LICENSE
README.md
setup.py
densired/__init__.py
densired/datagen.py
densired/seed_spreader.py
densired.egg-info/PKG-INFO
densired.egg-info/SOURCES.txt
densired.egg-info/dependency_links.txt
densired.egg-info/requires.txt
densired.egg-info/top_level.txt