Metadata-Version: 2.1
Name: densired
Version: 1.2.0
Summary: A generator for density-based data
Home-page: https://github.com/PhilJahn/DENSIRED
Author: Philipp Jahn
Author-email: jahn@dbs.ifi.lmu.de
License: MIT
Classifier: Development Status :: 3 - Alpha
Classifier: Intended Audience :: Science/Research
Classifier: License :: OSI Approved :: MIT License
Classifier: Operating System :: POSIX :: Linux
Classifier: Operating System :: Microsoft :: Windows
Classifier: Programming Language :: Python :: 3.9
License-File: LICENSE
Requires-Dist: matplotlib
Requires-Dist: numpy>=2.0.1
Requires-Dist: scipy
